libzfs_core/_constants.py
libzfs_core/exceptions.py
libzfs_core/_error_translation.py
libzfs_core/_libzfs_core.py
libzfs_core/ctypes.py
libzfs_core/__init__.py
libzfs_core/_nvlist.py
libzfs_core/test/__init__.py
libzfs_core/test/test_libzfs_core.py
libzfs_core/test/test_nvlist.py
libzfs_core/bindings/__init__.py
libzfs_core/bindings/libzfs_core.py
libzfs_core/bindings/libnvpair.py
pyzfs-0.2.3.dist-info/WHEEL
pyzfs-0.2.3.dist-info/top_level.txt
pyzfs-0.2.3.dist-info/metadata.json
pyzfs-0.2.3.dist-info/RECORD
pyzfs-0.2.3.dist-info/METADATA
pyzfs-0.2.3.dist-info/DESCRIPTION.rst
