Metadata-Version: 2.0
Name: pyzfs
Version: 0.2.3
Summary: Wrapper for libzfs_core
Home-page: http://pyzfs.readthedocs.org
Author: ClusterHQ
Author-email: support@clusterhq.com
License: Apache License, Version 2.0
Keywords: ZFS,OpenZFS,libzfs_core
Platform: UNKNOWN
Classifier: Development Status :: 4 - Beta
Classifier: Intended Audience :: Developers
Classifier: License :: OSI Approved :: Apache Software License
Classifier: Programming Language :: Python :: 2 :: Only
Classifier: Programming Language :: Python :: 2.7
Classifier: Topic :: System :: Filesystems
Classifier: Topic :: Software Development :: Libraries
Requires-Dist: cffi
